hypersequence/__init__.py
hypersequence-0.10.0.dist-info/LICENSE
hypersequence-0.10.0.dist-info/METADATA
hypersequence-0.10.0.dist-info/WHEEL
hypersequence-0.10.0.dist-info/top_level.txt
hypersequence-0.10.0.dist-info/RECORD
