Metadata-Version: 2.1
Name: hypersequence
Version: 0.10.0
Summary: HyperSequence is a data format and library for super-fast training of large machine learning datasets
Home-page: https://gitlab.com/vvanbeveren/hypersequence
Author: Vincent van Beveren
Author-email: vvanbeveren@gmail.com
License: MIT License
Platform: all
Classifier: Programming Language :: Python :: 3
Classifier: Programming Language :: Python :: 3.6
Classifier: License :: OSI Approved :: MIT License
Classifier: Operating System :: OS Independent
Requires-Python: >=3.6
License-File: LICENSE
Requires-Dist: numpy (>=1.2)
